par_segmentation/__init__.py
par_segmentation/_tgf_interpolate.py
par_segmentation/funcs.py
par_segmentation/interactive.py
par_segmentation/legacy.py
par_segmentation/model_base.py
par_segmentation/model_de.py
par_segmentation/model_flexi.py
par_segmentation/model_gd.py
par_segmentation/quantifier.py
par_segmentation/roi.py
par_segmentation-0.1.16.dist-info/LICENSE
par_segmentation-0.1.16.dist-info/METADATA
par_segmentation-0.1.16.dist-info/WHEEL
par_segmentation-0.1.16.dist-info/top_level.txt
par_segmentation-0.1.16.dist-info/RECORD
