Metadata-Version: 2.1
Name: par_segmentation
Version: 0.1.16
Summary: Cell cortex segmentation and quantification in C. elegans PAR protein images
Author-email: Tom Bland <tom_bland@hotmail.co.uk>
License: Attribution 4.0 International
Project-URL: Documentation, https://par-segmentation.readthedocs.io/
Project-URL: Source, https://github.com/goehringlab/par-segmentation
Requires-Python: >=3.11
License-File: LICENSE
Requires-Dist: numpy
Requires-Dist: matplotlib
Requires-Dist: scipy
Requires-Dist: scikit-image
Requires-Dist: joblib
Requires-Dist: tqdm
Requires-Dist: pandas
Requires-Dist: absl-py
Requires-Dist: matplotlib-polyroi >=0.1.6
Requires-Dist: ipykernel
Requires-Dist: ipympl
Provides-Extra: all
Requires-Dist: par-segmentation[dev,doc,jax,tensorflow] ; extra == 'all'
Provides-Extra: dev
Requires-Dist: pytest ; extra == 'dev'
Requires-Dist: pre-commit ; extra == 'dev'
Requires-Dist: black ; extra == 'dev'
Requires-Dist: pip-tools ; extra == 'dev'
Requires-Dist: pytest-cov ; extra == 'dev'
Requires-Dist: nbformat ; extra == 'dev'
Requires-Dist: nbconvert ; extra == 'dev'
Provides-Extra: doc
Requires-Dist: sphinx-rtd-theme ==1.0.0 ; extra == 'doc'
Provides-Extra: jax
Requires-Dist: jax ; extra == 'jax'
Requires-Dist: optax ; extra == 'jax'
Provides-Extra: tensorflow
Requires-Dist: tensorflow >=2.9.1 ; extra == 'tensorflow'
